modular_noc_scheduling-1.0.8.dist-info/licenses/LICENSE
modular_scheduling/__init__.py
modular_scheduling/modular_scheduler.py
modular_scheduling/solution_format_printer.py
modular_scheduling/utils.py
modular_scheduling/constraints/__init__.py
modular_scheduling/constraints/base_constraint.py
modular_scheduling/constraints/contiguous_shifts_limit_constraint.py
modular_scheduling/constraints/evening_night_rest_constraint.py
modular_scheduling/constraints/evening_shifts_minimum_constraint.py
modular_scheduling/constraints/expert_supervision_constraint.py
modular_scheduling/constraints/fair_distribution_constraint.py
modular_scheduling/constraints/holiday_shifts_constraint.py
modular_scheduling/constraints/off_day_exclusivity_constraint.py
modular_scheduling/constraints/one_shift_per_day_constraint.py
modular_scheduling/constraints/shifts_distribution_constraint.py
modular_scheduling/constraints/vacation_based_off_days_constraint.py
modular_scheduling/constraints/weekday_shifts_constraint.py
modular_scheduling/constraints/weekend_shifts_constraint.py
pyarmor_runtime_000000/__init__.py
pyarmor_runtime_000000/pyarmor_runtime.pyd
modular_noc_scheduling-1.0.8.dist-info/METADATA
modular_noc_scheduling-1.0.8.dist-info/WHEEL
modular_noc_scheduling-1.0.8.dist-info/entry_points.txt
modular_noc_scheduling-1.0.8.dist-info/top_level.txt
modular_noc_scheduling-1.0.8.dist-info/RECORD
