Metadata-Version: 2.4
Name: modular-noc-scheduling
Version: 1.0.8
Summary: Shift Scheduling Algorithm using OR-Tools with Modular Constraints
Author: Innovation Team - Digital Transformation Directorate
Maintainer: Innovation Team - Digital Transformation Directorate
License: MIT
Project-URL: Homepage, https://github.com/abdalkarimnael/scheduling_package
Project-URL: Repository, https://github.com/abdalkarimnael/scheduling_package
Project-URL: Documentation, https://github.com/abdalkarimnael/scheduling_package#readme
Project-URL: Bug Reports, https://github.com/abdalkarimnael/scheduling_package/issues
Keywords: scheduling,optimization,constraint-programming,ortools,employee-scheduling,shift-scheduling,noc-scheduling,ramadan-scheduling,holiday-scheduling,workforce-management
Classifier: Development Status :: 4 - Beta
Classifier: Intended Audience :: Developers
Classifier: Intended Audience :: Information Technology
Classifier: License :: OSI Approved :: MIT License
Classifier: Operating System :: OS Independent
Classifier: Programming Language :: Python :: 3
Classifier: Programming Language :: Python :: 3.8
Classifier: Programming Language :: Python :: 3.9
Classifier: Programming Language :: Python :: 3.10
Classifier: Programming Language :: Python :: 3.11
Classifier: Programming Language :: Python :: 3.12
Classifier: Programming Language :: Python :: 3.13
Classifier: Topic :: Office/Business :: Scheduling
Classifier: Topic :: Scientific/Engineering :: Mathematics
Classifier: Topic :: Software Development :: Libraries :: Python Modules
Requires-Python: >=3.8
License-File: LICENSE
Requires-Dist: ortools>=9.0.0
Requires-Dist: hijri-converter>=2.2.4
Provides-Extra: ui
Requires-Dist: streamlit>=1.28.0; extra == "ui"
Requires-Dist: pandas>=1.5.0; extra == "ui"
Provides-Extra: dev
Requires-Dist: pytest>=7.0.0; extra == "dev"
Requires-Dist: pytest-cov>=4.0.0; extra == "dev"
Requires-Dist: black>=22.0.0; extra == "dev"
Requires-Dist: flake8>=5.0.0; extra == "dev"
Requires-Dist: mypy>=1.0.0; extra == "dev"
Requires-Dist: pre-commit>=2.20.0; extra == "dev"
Provides-Extra: docs
Requires-Dist: sphinx>=5.0.0; extra == "docs"
Requires-Dist: sphinx-rtd-theme>=1.0.0; extra == "docs"
Requires-Dist: myst-parser>=0.18.0; extra == "docs"
Dynamic: license-file
